[
    {
        "key": "dbln",
        "value": "%7B%22100044772673426%22%3A%22u0VcCIte%22%7D",
        "domain": "facebook.com",
        "path": "/login/device-based/",
        "hostOnly": false,
        "creation": "2025-10-10T14:24:44.219Z",
        "lastAccessed": "2025-10-10T14:24:44.220Z"
    },
    {
        "key": "datr",
        "value": "Yl3oaCoic-bhZH3U8MXjB7B3",
        "domain": "facebook.com",
        "path": "/",
        "hostOnly": false,
        "creation": "2025-10-10T14:24:44.220Z",
        "lastAccessed": "2025-10-10T14:24:44.220Z"
    },
    {
        "key": "sb",
        "value": "Yl3oaOYaZy-zcMebVj2z7hES",
        "domain": "facebook.com",
        "path": "/",
        "hostOnly": false,
        "creation": "2025-10-10T14:24:44.220Z",
        "lastAccessed": "2025-10-10T14:24:44.220Z"
    },
    {
        "key": "ps_l",
        "value": "1",
        "domain": "facebook.com",
        "path": "/",
        "hostOnly": false,
        "creation": "2025-10-10T14:24:44.221Z",
        "lastAccessed": "2025-10-10T14:24:44.221Z"
    },
    {
        "key": "ps_n",
        "value": "1",
        "domain": "facebook.com",
        "path": "/",
        "hostOnly": false,
        "creation": "2025-10-10T14:24:44.221Z",
        "lastAccessed": "2025-10-10T14:24:44.221Z"
    },
    {
        "key": "pas",
        "value": "100044772673426%3AHUjSQ4OmaS",
        "domain": "facebook.com",
        "path": "/",
        "hostOnly": false,
        "creation": "2025-10-10T14:24:44.221Z",
        "lastAccessed": "2025-10-10T14:24:44.221Z"
    },
    {
        "key": "locale",
        "value": "bn_IN",
        "domain": "facebook.com",
        "path": "/",
        "hostOnly": false,
        "creation": "2025-10-10T14:24:44.221Z",
        "lastAccessed": "2025-10-10T14:24:44.221Z"
    },
    {
        "key": "vpd",
        "value": "v1%3B730x384x1.875",
        "domain": "facebook.com",
        "path": "/",
        "hostOnly": false,
        "creation": "2025-10-10T14:24:44.221Z",
        "lastAccessed": "2025-10-10T14:24:44.221Z"
    },
    {
        "key": "c_user",
        "value": "100044772673426",
        "domain": "facebook.com",
        "path": "/",
        "hostOnly": false,
        "creation": "2025-10-10T14:24:44.221Z",
        "lastAccessed": "2025-10-10T14:24:44.221Z"
    },
    {
        "key": "xs",
        "value": "24%3Agy2Atv9XgAPF7A%3A2%3A1760102048%3A-1%3A-1",
        "domain": "facebook.com",
        "path": "/",
        "hostOnly": false,
        "creation": "2025-10-10T14:24:44.221Z",
        "lastAccessed": "2025-10-10T14:24:44.221Z"
    },
    {
        "key": "fr",
        "value": "0FsPWu3IUjGEyH3fk.AWcVEtNQRLH8B2IaVHuGWuSnefQTyjPgU13lP4DCKVNU_Y0MUao.Bo6F1i..AAA.0.0.Bo6Qal.AWdB8xSlQeVvoLPuSypWjCIQA3k",
        "domain": "facebook.com",
        "path": "/",
        "hostOnly": false,
        "creation": "2025-10-10T14:24:44.221Z",
        "lastAccessed": "2025-10-10T14:24:44.221Z"
    },
    {
        "key": "wl_cbv",
        "value": "v2%3Bclient_version%3A2949%3Btimestamp%3A1760106128",
        "domain": "facebook.com",
        "path": "/",
        "hostOnly": false,
        "creation": "2025-10-10T14:24:44.221Z",
        "lastAccessed": "2025-10-10T14:24:44.221Z"
    },
    {
        "key": "fbl_st",
        "value": "101426560%3BT%3A29335102",
        "domain": "facebook.com",
        "path": "/",
        "hostOnly": false,
        "creation": "2025-10-10T14:24:44.221Z",
        "lastAccessed": "2025-10-10T14:24:44.221Z"
    }
]
